{
  "examples": {
    "dynamic_routing": {
      "example": "dynamic_routing",
      "metadata": {
        "example": "dynamic_routing",
        "updated_at": "2025-11-17T12:47:59.382017"
      },
      "metrics": {
        "baseline_p75_ms": 0.9763200283050537,
        "baseline_throughput.latency_ms": 0.956824004650116,
        "baseline_throughput.requests_per_s": 66887.95399045515,
        "baseline_throughput.schemaVersion": "1.0",
        "baseline_throughput.tokens_per_s": 8561658.11077826,
        "baseline_time_ms": 0.956824004650116,
        "best_optimized_p75_ms": 5.517024040222168,
        "best_optimized_speedup": 1.05,
        "best_optimized_throughput.latency_ms": 7.263048052787781,
        "best_optimized_throughput.requests_per_s": 35246.90985649466,
        "best_optimized_throughput.tokens_per_s": 4511604.461631317,
        "best_optimized_time_ms": 6.6487040519714355,
        "best_speedup": 1.05
      },
      "type": "python"
    },
    "inference_full": {
      "example": "inference_full",
      "metadata": {
        "example": "inference_full",
        "updated_at": "2025-11-17T12:47:59.382017"
      },
      "metrics": {
        "baseline_p75_ms": 2.168735980987549,
        "baseline_throughput.latency_ms": 1.878933117389679,
        "baseline_throughput.requests_per_s": 8515.470748755608,
        "baseline_throughput.schemaVersion": "1.0",
        "baseline_throughput.tokens_per_s": 17439684.093451485,
        "baseline_time_ms": 1.878933117389679,
        "best_optimized_p75_ms": 0.9153919816017151,
        "best_optimized_speedup": 3.2759283539706296,
        "best_optimized_throughput.latency_ms": 1.2881081676483155,
        "best_optimized_throughput.requests_per_s": 12421.31709265614,
        "best_optimized_throughput.tokens_per_s": 25438857.405759774,
        "best_optimized_time_ms": 0.7791193580627441,
        "best_speedup": 3.2759283539706296
      },
      "type": "python"
    },
    "memory": {
      "example": "memory",
      "metadata": {
        "best_optimization": "optimized_memory",
        "best_optimization_file": "optimized_memory.py",
        "best_optimization_speedup": 6.497702911161493,
        "best_optimization_time_ms": 5.71410302400589,
        "example": "memory",
        "git_commit": "299917c12cd44f5041355355c79b81a4b1b387b4",
        "updated_at": "2025-11-17T13:30:15.220776"
      },
      "metrics": {
        "baseline_p75_ms": 38.5002555847168,
        "baseline_throughput.latency_ms": 37.128543853759766,
        "baseline_throughput.requests_per_s": 215.46764751965603,
        "baseline_throughput.schemaVersion": "1.0",
        "baseline_throughput.tokens_per_s": 225934203.96557084,
        "baseline_time_ms": 37.128543853759766,
        "best_optimized_p75_ms": 5.975008010864258,
        "best_optimized_speedup": 6.497702911161493,
        "best_optimized_throughput.latency_ms": 5.71410302400589,
        "best_optimized_throughput.requests_per_s": 1400.0447605495874,
        "best_optimized_throughput.tokens_per_s": 1468053334.8380442,
        "best_optimized_time_ms": 5.71410302400589,
        "best_speedup": 6.497702911161493
      },
      "type": "python"
    },
    "pipeline_parallelism": {
      "example": "pipeline_parallelism",
      "metadata": {
        "example": "pipeline_parallelism",
        "updated_at": "2025-11-17T12:47:59.382017"
      },
      "metrics": {
        "baseline_p75_ms": 2.9178879261016846,
        "baseline_throughput.latency_ms": 2.4801263988018034,
        "baseline_throughput.requests_per_s": 403.20525618497476,
        "baseline_throughput.samples_per_s": 103220.54558335354,
        "baseline_throughput.schemaVersion": "1.0",
        "baseline_throughput.tokens_per_s": 105697838.67735402,
        "baseline_time_ms": 2.4801263988018034,
        "best_optimized_p75_ms": 2.033535957336426,
        "best_optimized_speedup": 4.8750097745544485,
        "best_optimized_throughput.latency_ms": 2.000154654184977,
        "best_optimized_throughput.requests_per_s": 1999.8453577730568,
        "best_optimized_throughput.tokens_per_s": 131061865.36701505,
        "best_optimized_time_ms": 2.000154654184977,
        "best_speedup": 4.8750097745544485
      },
      "type": "python"
    },
    "prefill_decode_disagg": {
      "example": "prefill_decode_disagg",
      "metadata": {
        "example": "prefill_decode_disagg",
        "updated_at": "2025-11-17T12:47:59.382017"
      },
      "metrics": {
        "baseline_p75_ms": 6.025279998779297,
        "baseline_throughput.latency_ms": 5.6367871284484865,
        "baseline_throughput.requests_per_s": 177.40602531414876,
        "baseline_throughput.schemaVersion": "1.0",
        "baseline_throughput.tokens_per_s": 48254.438885448464,
        "baseline_time_ms": 5.6367871284484865,
        "best_optimized_p75_ms": 41.927425384521484,
        "best_optimized_speedup": 1.2981879510190166,
        "best_optimized_throughput.latency_ms": 41.40733757019043,
        "best_optimized_throughput.requests_per_s": 193.20247254339975,
        "best_optimized_throughput.tokens_per_s": 445138.496739993,
        "best_optimized_time_ms": 41.40733757019043,
        "best_speedup": 1.2981879510190166
      },
      "type": "python"
    },
    "prefill_decode_disagg_multigpu": {
      "example": "prefill_decode_disagg_multigpu",
      "metadata": {
        "example": "prefill_decode_disagg_multigpu",
        "updated_at": "2025-11-17T12:47:59.382017"
      },
      "metrics": {
        "best_optimized_speedup": 1.05,
        "best_speedup": 1.05
      },
      "type": "python"
    },
    "routing_static": {
      "example": "routing_static",
      "metadata": {
        "best_optimization": "optimized_routing_static",
        "best_optimization_file": "optimized_routing_static.py",
        "best_optimization_speedup": 2.1763537628241845,
        "best_optimization_time_ms": 5.461354179382324,
        "example": "routing_static",
        "git_commit": "299917c12cd44f5041355355c79b81a4b1b387b4",
        "updated_at": "2025-11-17T13:30:37.734318"
      },
      "metrics": {
        "baseline_p75_ms": 11.908063888549805,
        "baseline_throughput.latency_ms": 12.009066257476807,
        "baseline_throughput.requests_per_s": 832.7042074377791,
        "baseline_throughput.schemaVersion": "1.0",
        "baseline_throughput.tokens_per_s": 27286051.469321147,
        "baseline_time_ms": 12.009066257476807,
        "best_optimized_p75_ms": 5.891327857971191,
        "best_optimized_speedup": 2.1763537628241845,
        "best_optimized_throughput.latency_ms": 5.461354179382324,
        "best_optimized_throughput.requests_per_s": 1831.047698344112,
        "best_optimized_throughput.tokens_per_s": 59999770.97933986,
        "best_optimized_time_ms": 5.461354179382324,
        "best_speedup": 2.1763537628241845
      },
      "type": "python"
    }
  },
  "hardware_key": "gb10"
}
