{
  "examples": {
    "roofline": {
      "example": "roofline",
      "metadata": {
        "best_optimization": "optimized_roofline",
        "best_optimization_file": "optimized_roofline.py",
        "best_optimization_speedup": 1.0,
        "best_optimization_time_ms": 0.0,
        "git_commit": "84606e9c19c12074b2a1b9c0c013914b934c4fe8",
        "updated_at": "2025-12-12T14:34:56.820735"
      },
      "metrics": {
        "baseline_time_ms": 0.0,
        "best_optimized_speedup": 1.0,
        "best_optimized_time_ms": 0.0,
        "best_speedup": 1.0
      },
      "type": "python"
    }
  },
  "hardware_key": "b200",
  "schema_version": 2
}
