{
  "examples": {
    "llama_3_1_8b": {
      "example": "llama_3_1_8b",
      "metadata": {
        "best_memory_savings_pct": 37.084984517925115,
        "best_memory_savings_ratio": 1.5894456869122284,
        "best_optimization": "optimized_llama_3_1_8b",
        "best_optimization_file": "optimized_llama_3_1_8b.py",
        "best_optimization_memory_mb": 2076.3134765625,
        "best_optimization_speedup": 2.5043968012370654,
        "best_optimization_technique": "optimized_llama_3_1_8b",
        "best_optimization_time_ms": 3.465445510272322,
        "optimization_goal": "speed"
      },
      "metrics": {
        "baseline_memory_mb": 3300.1875,
        "baseline_p75_ms": 8.602527618408203,
        "baseline_throughput.bytes_per_s": null,
        "baseline_throughput.custom_unit_name": null,
        "baseline_throughput.custom_unit_per_s": null,
        "baseline_throughput.goodput": null,
        "baseline_throughput.latency_ms": 8.678850650787354,
        "baseline_throughput.requests_per_s": 115.22263030408054,
        "baseline_throughput.samples_per_s": null,
        "baseline_throughput.schemaVersion": "1.0",
        "baseline_throughput.tokens_per_s": null,
        "baseline_time_ms": 8.678850650787354,
        "best_memory_savings_pct": 37.084984517925115,
        "best_memory_savings_ratio": 1.5894456869122284,
        "best_optimized_memory_mb": 2076.3134765625,
        "best_optimized_p75_ms": 3.5953919887542725,
        "best_optimized_speedup": 2.5043968012370654,
        "best_optimized_throughput.bytes_per_s": null,
        "best_optimized_throughput.custom_unit_name": null,
        "best_optimized_throughput.custom_unit_per_s": null,
        "best_optimized_throughput.goodput": null,
        "best_optimized_throughput.latency_ms": 3.465445510272322,
        "best_optimized_throughput.requests_per_s": 288.56318676366027,
        "best_optimized_throughput.samples_per_s": null,
        "best_optimized_throughput.schemaVersion": "1.0",
        "best_optimized_throughput.tokens_per_s": null,
        "best_optimized_time_ms": 3.465445510272322,
        "best_speedup": 2.5043968012370654,
        "is_regression": false
      },
      "provenance": {
        "git_commit": "6708ccd2f8f09db1d90f61db446c7d6bc4913f4d",
        "hardware_key": "b200",
        "iterations": 20,
        "profile_name": "none",
        "timestamp": "2025-12-19T01:36:56.661407",
        "warmup_iterations": 5
      },
      "type": "python"
    }
  },
  "hardware_key": "b200",
  "schema_version": 2
}
